airc_extract/__init__.py
airc_extract/airc_report.py
airc_extract/db_ops.py
airc_extract-0.2.3.dist-info/METADATA
airc_extract-0.2.3.dist-info/WHEEL
airc_extract-0.2.3.dist-info/entry_points.txt
airc_extract-0.2.3.dist-info/RECORD
