Metadata-Version: 2.4
Name: airc-extract
Version: 0.2.3
Summary: Extracts AIRC data from DICOM files and uploads to SQLite Database
Author-email: irdinsmore1 <irdinsmore1@geisinger.edu>
Requires-Python: >=3.11
Requires-Dist: loguru>=0.7.3
Requires-Dist: polars>=1.28.1
Requires-Dist: pydicom>=3.0.1
